pacote_de_metricas/metricas.py
pacote_de_metricas-0.0.2.dist-info/METADATA
pacote_de_metricas-0.0.2.dist-info/WHEEL
pacote_de_metricas-0.0.2.dist-info/top_level.txt
pacote_de_metricas-0.0.2.dist-info/RECORD
