Metadata-Version: 2.1
Name: pacote-de-metricas
Version: 0.0.2
Summary: Pacote para auxiliar nos cálculos de métricas dos scripts do projeto
Author-email: Darlan Sá <darlansaa@gmail.com>
Classifier: Programming Language :: Python :: 3
Classifier: License :: OSI Approved :: MIT License
Classifier: Operating System :: OS Independent
Requires-Python: >=3.7
